TwitchWebsocket/Message.py
TwitchWebsocket/TwitchWebsocket.py
TwitchWebsocket/__init__.py
TwitchWebsocket/__version__.py
TwitchWebsocket-1.2.1.dist-info/LICENSE
TwitchWebsocket-1.2.1.dist-info/METADATA
TwitchWebsocket-1.2.1.dist-info/WHEEL
TwitchWebsocket-1.2.1.dist-info/top_level.txt
TwitchWebsocket-1.2.1.dist-info/RECORD
