Metadata-Version: 2.1
Name: TwitchWebsocket
Version: 1.2.1
Summary: Python Wrapper for easily connecting to Twitch and setting up a chat bot.
Home-page: https://github.com/CubieDev/TwitchWebsocket
Author: Tom Aarsen
Author-email: cubiegamedev@gmail.com
License: MIT
Platform: UNKNOWN
Classifier: License :: OSI Approved :: MIT License
Classifier: Programming Language :: Python
Classifier: Programming Language :: Python :: 3
Classifier: Programming Language :: Python :: 3.6
Classifier: Programming Language :: Python :: 3.7
Classifier: Programming Language :: Python :: 3.8
Classifier: Programming Language :: Python :: Implementation :: CPython
Classifier: Programming Language :: Python :: Implementation :: PyPy
Requires-Python: >=3.6.0
